dunzo/__init__.py
dunzo/cli.py
dunzo/done.py
dunzo/sound_effects/dog.wav
dunzo/sound_effects/flute.wav
dunzo/sound_effects/game.wav
dunzo-0.1.2.dist-info/entry_points.txt
dunzo-0.1.2.dist-info/WHEEL
dunzo-0.1.2.dist-info/METADATA
dunzo-0.1.2.dist-info/RECORD
