Metadata-Version: 2.1
Name: dunzo
Version: 0.1.2
Summary: 
Requires-Python: >=3.7,<4.0
Classifier: Programming Language :: Python :: 3
Classifier: Programming Language :: Python :: 3.10
Classifier: Programming Language :: Python :: 3.7
Classifier: Programming Language :: Python :: 3.8
Classifier: Programming Language :: Python :: 3.9
Requires-Dist: click (>=8.1.1,<9.0.0)
Requires-Dist: playsound (>=1.3.0,<2.0.0)
Requires-Dist: pyobjc (>=8.4.1,<9.0.0)
